cvkan/__init__.py
cvkan/experiments/__init__.py
cvkan/experiments/fit_formulas.py
cvkan/experiments/knot_dataset.py
cvkan/experiments/run_crossval.py
cvkan/models/CVKAN.py
cvkan/models/FastKAN.py
cvkan/models/__init__.py
cvkan/models/functions/CV_LayerNorm.py
cvkan/models/functions/ComplexSilu.py
cvkan/models/functions/__init__.py
cvkan/models/wrapper/CVKANWrapper.py
cvkan/models/wrapper/PyKANWrapper.py
cvkan/models/wrapper/WrapperTemplate.py
cvkan/models/wrapper/__init__.py
cvkan/train/__init__.py
cvkan/train/train_loop.py
cvkan/utils/__init__.py
cvkan/utils/eval_model.py
cvkan/utils/explain_kan.py
cvkan/utils/json_editor.py
cvkan/utils/loss_functions.py
cvkan/utils/misc.py
cvkan/utils/dataloading/__init__.py
cvkan/utils/dataloading/create_complex_dataset.py
cvkan/utils/dataloading/crossval_splitter.py
cvkan/utils/dataloading/csv_dataloader.py
cvkan/utils/latex/__init__.py
cvkan/utils/latex/latex_table_creator.py
cvkan/utils/plotting/__init__.py
cvkan/utils/plotting/cplot.py
cvkan/utils/plotting/cplotting_tools.py
cvkan/utils/plotting/plot_kan.py
cvkan-1.0.1.dist-info/licenses/LICENSE.md
images/__init__.py
images/visualizations.py
cvkan-1.0.1.dist-info/METADATA
cvkan-1.0.1.dist-info/WHEEL
cvkan-1.0.1.dist-info/top_level.txt
cvkan-1.0.1.dist-info/RECORD
