Metadata-Version: 2.4
Name: cvkan
Version: 1.0.1
Summary: CVKAN: Complex-Valued Kolmogorov-Arnold Networks
Author-email: Matthias Wolff <matthias.wolff@uni-muenster.de>, Florian Eilers <florian.eilers@uni-muenster.de>, Xiaoyi Jiang <xjiang@uni-muenster.de>
Project-URL: homepage, https://github.com/M-Wolff/CVKAN
Project-URL: github, https://github.com/M-Wolff/CVKAN
Project-URL: issues, https://github.com/M-Wolff/CVKAN/issues
Project-URL: arxiv, https://arxiv.org/abs/2502.02417
License-File: LICENSE.md
Requires-Dist: matplotlib==3.6.2
Requires-Dist: numpy==1.24.4
Requires-Dist: pandas==2.2.3
Requires-Dist: pykan==0.2.7
Requires-Dist: scikit_learn==1.6.1
Requires-Dist: torch==2.4.1
Requires-Dist: torchmetrics==1.6.1
Requires-Dist: scikit-learn~=1.6.1
Requires-Dist: plumbum~=1.9.0
Requires-Dist: pyyaml==6.0.2
Requires-Dist: tqdm==4.67.1
Dynamic: license-file
